tjaf/__init__.py
tjaf-1.0.6.dist-info/METADATA
tjaf-1.0.6.dist-info/WHEEL
tjaf-1.0.6.dist-info/top_level.txt
tjaf-1.0.6.dist-info/RECORD
