Metadata-Version: 2.1
Name: tjaf
Version: 1.0.6
Summary: TJA decoder in Python
Home-page: https://github.com/yuukialpha/tjaf
Author: Yuuki
Author-email: skifree@skiff.com
